{"stem":"00664","instances":[{"docId":"e00664_1450-12-02","docUri":"e00664_1450-12-02.html","score":2,"contexts":[{"form":"00664","weight":"1","pos":210,"context":"Eintrag vom 1450-12-02, Nr. <mark>00664<\/mark>, In: Ertl, Thomas\/Andorfer, Peter...","fid":"page"},{"form":"00664","weight":"1","pos":237,"context":"...: https:\/\/grundbuecher.acdh.oeaw.ac.at\/e<mark>00664<\/mark>_1450-12-02.html","fid":"page"}]},{"docId":"toc","docUri":"toc.html","score":1,"contexts":[{"form":"00664","weight":"1","pos":14382,"context":"e<mark>00664<\/mark>_1450-12-02.xml","fid":"tocTable"}]}]}