{"stem":"01956","instances":[{"docId":"e01956_1462-03-31","docUri":"e01956_1462-03-31.html","score":2,"contexts":[{"form":"01956","weight":"1","pos":107,"context":"Eintrag vom 1462-03-31, Nr. <mark>01956<\/mark>, In: Ertl, Thomas\/Andorfer, Peter...","fid":"page"},{"form":"01956","weight":"1","pos":134,"context":"...: https:\/\/grundbuecher.acdh.oeaw.ac.at\/e<mark>01956<\/mark>_1462-03-31.html","fid":"page"}]},{"docId":"toc","docUri":"toc.html","score":1,"contexts":[{"form":"01956","weight":"1","pos":15750,"context":"e<mark>01956<\/mark>_1462-03-31.xml","fid":"tocTable"}]}]}