{"stem":"munsser","instances":[{"docId":"e01383_1438-09-17","docUri":"e01383_1438-09-17.html","score":2,"contexts":[{"form":"munsser","weight":"1","pos":26,"context":"...xlviii tl. d. dafúr im Michel von Friesach der <mark>munsser<\/mark> und Kathrey sein hausfraw, ir haus vor Stubentor...","fid":"d1392e186"},{"form":"Munsser","weight":"1","pos":35,"context":"...ir haus vor Stubentor aufm Graben zenachst Seifrids des <mark>Munsser<\/mark> haus gelegen, zu phant gesaczt habent, verschriben...","fid":"d1392e186"}]},{"docId":"e00295_1440-04-22","docUri":"e00295_1440-04-22.html","score":1,"contexts":[{"form":"munsser","weight":"1","pos":23,"context":"Dorothe Hannsen Ofner des <mark>munsser<\/mark> hausfraw hat versaczt ir haws, gelegen in der...","fid":"d300e185"}]},{"docId":"e00936_1442-06-06","docUri":"e00936_1442-06-06.html","score":1,"contexts":[{"form":"Munsser","weight":"1","pos":50,"context":"...seins hauss, gelegen in Sant Johannsstrass zenagst Micheln <mark>Munsser<\/mark> haus, uber die fünftzig pfunt pfening, dafur...","fid":"d946e187"}]},{"docId":"e00610_1448-05-29","docUri":"e00610_1448-05-29.html","score":1,"contexts":[{"form":"munsser","weight":"1","pos":23,"context":"Hanns Ofner, <mark>munsser<\/mark>, und Dorothe, sein hausfrau, habent verchaufft...","fid":"d621e185"}]},{"docId":"e00538_1444-05-06","docUri":"e00538_1444-05-06.html","score":1,"contexts":[{"form":"Munsser","weight":"1","pos":41,"context":"..., gelegen vor Stubentor auf der Wienn zenagst Hainreichs <mark>Munsser<\/mark> haus, davon man jèrlich dint hincz Sand Larenczen...","fid":"d548e187"}]},{"docId":"e01677_1446-04-01","docUri":"e01677_1446-04-01.html","score":1,"contexts":[{"form":"munsser","weight":"1","pos":37,"context":"...vor Stubentor auf dem graben zenagst Hannsen Wugster des <mark>munsser<\/mark> haus, davon man jerlich dint zu der ewigen...","fid":"d1691e186"}]},{"docId":"e00967_1448-06-19","docUri":"e00967_1448-06-19.html","score":1,"contexts":[{"form":"Munsser","weight":"1","pos":35,"context":"...das ettwan ain ramhof gewesen ist zenagst Micheln des <mark>Munsser<\/mark> haus. Dem erbern Mertten Weidacher und Margrethen,...","fid":"d977e185"}]},{"docId":"e00924_1439-12-14","docUri":"e00924_1439-12-14.html","score":1,"contexts":[{"form":"munsser","weight":"1","pos":21,"context":"...haus, dacz er von Micheln von Friesach dem <mark>munsser<\/mark> gechaufft hat, gelegen vor Stubentor auf dem graben zenagst...","fid":"d936e185"}]},{"docId":"e01158_1452-04-28","docUri":"e01158_1452-04-28.html","score":1,"contexts":[{"form":"Munsser","weight":"1","pos":60,"context":"...tochter, die si mit irm erern mann Tobias <mark>Munsser<\/mark> seligen gehabt hat nach lautt ains saczbriefs und der...","fid":"d1168e197"}]},{"docId":"e00463_1439-06-12","docUri":"e00463_1439-06-12.html","score":1,"contexts":[{"form":"munsser","weight":"1","pos":30,"context":"...gelegen vor Stubentor aufm graben zenagst Hansen Wuchster des <mark>munsser<\/mark> haus, uber die sechs pfunt pfening dafur es...","fid":"d472e185"}]},{"docId":"e00686_1452-03-22","docUri":"e00686_1452-03-22.html","score":1,"contexts":[{"form":"munsser","weight":"1","pos":22,"context":"Hanns Ofner, <mark>munsser<\/mark> und Dorothe sein hausfrau habent verchaufft ain phund gelts...","fid":"d697e191"}]},{"docId":"e00548_1445-02-26","docUri":"e00548_1445-02-26.html","score":1,"contexts":[{"form":"munsser","weight":"1","pos":23,"context":"Hanns Maurperger, der <mark>munsser<\/mark>, hat versaczt sein haus, gelegen in der...","fid":"d558e185"}]},{"docId":"e01700_1450-03-27","docUri":"e01700_1450-03-27.html","score":1,"contexts":[{"form":"Munsser","weight":"1","pos":39,"context":"...gelts purkrechts auf irm halben haus das etwan Tobias <mark>Munsser<\/mark> gewesen ist, und allen den gemechen und gemainen stukchen...","fid":"d1715e186"}]},{"docId":"e01667_1443-04-10","docUri":"e01667_1443-04-10.html","score":1,"contexts":[{"form":"munsser","weight":"1","pos":35,"context":"...vor Stubentor auf dem graben zenagst Hansen Wugster des <mark>munsser<\/mark> haus, davon man jerlich dint zu der mess...","fid":"d1681e183"}]},{"docId":"e01151_1450-03-27","docUri":"e01151_1450-03-27.html","score":1,"contexts":[{"form":"Munsser","weight":"1","pos":48,"context":"..., die sy mit irm erern mann Thobias dem <mark>Munsser<\/mark> seligen gehabt hat, umb newnczig phunt Wienner pfenning,...","fid":"d1161e186"}]},{"docId":"e00579_1446-09-23","docUri":"e00579_1446-09-23.html","score":1,"contexts":[{"form":"Munsser","weight":"1","pos":33,"context":"..., gelegen vor Stubentor auf der Wienn zenagst Hainreichs <mark>Munsser<\/mark> haus. Uber die ii ½ tl. d. gelts...","fid":"d589e185"}]},{"docId":"e01826_1444-08-21","docUri":"e01826_1444-08-21.html","score":1,"contexts":[{"form":"munsser","weight":"1","pos":23,"context":"Ulreich Mewsl, der <mark>munsser<\/mark>, und Kunigund, sein hausfrau, habent verkaufft...","fid":"d1842e186"}]},{"docId":"e00504_1442-02-21","docUri":"e00504_1442-02-21.html","score":1,"contexts":[{"form":"munsser","weight":"1","pos":23,"context":"Hanns Ofnér, <mark>munsser<\/mark>, und Dorothe, sein hausfraw, habent verkaufft...","fid":"d513e185"}]},{"docId":"e01818a_1442-11-26","docUri":"e01818a_1442-11-26.html","score":1,"contexts":[{"form":"munsser","weight":"1","pos":23,"context":"Ulreich Meusel, der <mark>munsser<\/mark>, mitburger zu Wien, und Kunigund, sein...","fid":"d1834e186"}]}]}