{"stem":"obsser","instances":[{"docId":"e00309_1455-07-16","docUri":"e00309_1455-07-16.html","score":1,"contexts":[{"form":"obsser","weight":"1","pos":84,"context":"...und nicht mer. Dem erbern Jorgen Prantner, <mark>obsser<\/mark>, und Anna seiner hausfraun und irn paiden erben...","fid":"d314e183"}]},{"docId":"e01589a_1456-09-22","docUri":"e01589a_1456-09-22.html","score":1,"contexts":[{"form":"obsser","weight":"1","pos":39,"context":"...tail und an dem andern zenagst Ulreichs Strúczl des <mark>obsser<\/mark> haus. Der erbern Barbaren, Hannsen Werglperger hausfraun...","fid":"d1602e185"}]},{"docId":"e01683_1447-06-02","docUri":"e01683_1447-06-02.html","score":1,"contexts":[{"form":"obsser","weight":"1","pos":23,"context":"Stephan Radendorffer, der <mark>obsser<\/mark>, und Kathrey, sein hausfrau, habent versaczt...","fid":"d1697e186"}]},{"docId":"e01687_1448-05-27","docUri":"e01687_1448-05-27.html","score":1,"contexts":[{"form":"obsser","weight":"1","pos":23,"context":"Steffan Radendorffer, <mark>obsser<\/mark>, und Kathrey, sein hausfraw, habent versaczt...","fid":"d1701e186"}]},{"docId":"e00756_1456-06-18","docUri":"e00756_1456-06-18.html","score":1,"contexts":[{"form":"obsser","weight":"1","pos":23,"context":"Hanns Holer, <mark>obsser<\/mark>, und Barbara sein hausfrau habent versaczt ir haus...","fid":"d767e191"}]}]}