{"stem":"urbetschen","instances":[{"docId":"e00591_1447-06-09","docUri":"e00591_1447-06-09.html","score":1,"contexts":[{"form":"Urbetschen","weight":"1","pos":43,"context":"...Hannsen Veltpekchen, caplan der mess so die · <mark>Urbetschen<\/mark> auf der Zwelfpoten altar zu Sand Steffan gesftifft habent...","fid":"d602e186"}]},{"docId":"e01864_1457-03-30","docUri":"e01864_1457-03-30.html","score":1,"contexts":[{"form":"Urbetschen","weight":"1","pos":62,"context":"...zu Sant Steffan dieczeit verweser der mess so die <mark>Urbetschen<\/mark> auf sant Valteins altar in sant Peter gestifft habent...","fid":"d1881e186"}]},{"docId":"e01860_1456-09-22","docUri":"e01860_1456-09-22.html","score":1,"contexts":[{"form":"Urbetschen","weight":"1","pos":76,"context":"...Sant Steffan, dieczeit verweser der mess so die <mark>Urbetschen<\/mark> auf Sand Valteins altar zu Sant Peter gestifft habent...","fid":"d1876e186"}]},{"docId":"e00460_1439-03-11","docUri":"e00460_1439-03-11.html","score":1,"contexts":[{"form":"Urbetschen","weight":"1","pos":32,"context":"...Hannsen Veldpekchen, verweser der ewigen mess so die <mark>Urbetschen<\/mark> auf der zwelfboten altar zu Sant Steffan gestifft habent...","fid":"d469e185"}]},{"docId":"e01874_1459-06-06","docUri":"e01874_1459-06-06.html","score":1,"contexts":[{"form":"Urbetschen","weight":"1","pos":62,"context":"...zu Sand Steffan dieczeit verweser der mess so die <mark>Urbetschen<\/mark> auf sand Valteins altar zu Sand Peter daselbs gestifft...","fid":"d1891e186"}]}]}