{"stem":"wert","instances":[{"docId":"e00736_1454-11-27","docUri":"e00736_1454-11-27.html","score":1,"contexts":[{"form":"wert","weight":"1","pos":132,"context":"...raihen und geben zehen fuder most, nach seim <mark>wert<\/mark> ye zweiwnddreissig emer fur ain fuder zeraitten, oder...","fid":"d747e191"}]},{"docId":"about","docUri":"about.html","score":1,"contexts":[{"form":"Wert","weight":"1","pos":1027,"context":"...keine Personallast. Entsprechend senkte ein bestehendes Burgrecht den <mark>Wert<\/mark> einer Immobilie. Häuser waren gelegentlich mit mehreren Burgrechten...","fid":"d6e244"}]},{"docId":"e00693_1452-06-21","docUri":"e00693_1452-06-21.html","score":1,"contexts":[{"form":"wert","weight":"1","pos":141,"context":"...raichen und geben zehen fuder most, nach seim <mark>wert<\/mark> ye zwenunddreissig emer fur ain fuder zeraitten oder aber...","fid":"d704e191"}]},{"docId":"e01258_1451-05-03","docUri":"e01258_1451-05-03.html","score":1,"contexts":[{"form":"werts","weight":"1","pos":74,"context":"...und den keller erlengen wurd gegen Hainreichs Niderhöfer haus <mark>werts<\/mark>, so sol der Schorffenperger denselben tail in dem...","fid":"d1267e197"}]},{"docId":"e01919_1445-09-20","docUri":"e01919_1445-09-20.html","score":1,"contexts":[{"form":"wert","weight":"1","pos":138,"context":"...nachkomen auf ain ander erbgut das des gelts wol <mark>wert<\/mark> sey sullen gelegt und verschriben werden in den rechten...","fid":"d1940e192"}]}]}