{"stem":"xliiioo","instances":[{"docId":"e01911_1443-07-05","docUri":"e01911_1443-07-05.html","score":2,"contexts":[{"form":"xliiioo","weight":"1","pos":16,"context":"..., consulis, Arnolt Galander, anno etc. <mark>xliiioo<\/mark>. Digitale Edition der Wiener Grundbücher | ","fid":"page"},{"form":"xliiioo","weight":"1","pos":130,"context":"..., consulis, Arnolt Galander, anno etc. <mark>xliiioo<\/mark>. Digitale Edition der Wiener Grundbücher ","fid":"exampleModalLongTitle"}]},{"docId":"toc","docUri":"toc.html","score":1,"contexts":[{"form":"xliiioo","weight":"1","pos":11807,"context":"..., consulis, Arnolt Galander, anno etc. <mark>xliiioo<\/mark>.","fid":"tocTable"}]}]}